{
  "page": 213,
  "section": "notation",
  "text": "ਗੰ ਗ ਗੰ ਗੰ ਰੇਂ ਰੇਂ ਸੱ ਸ\nਇ ਕਿ ਉਪ ਰਿ ਰਹ ਨਿ ਥ ੜੇ\nਨੀ ਨੀ ਨੀ ਨੀ ਧ ਧ ਧ ਧ\nਤਿ ਨਹਾ ਸਵਾ ਰੇ ਨਾ ਨ ਕਾ 8\nਪ ਮ ਗ ਰੇ ਸ ਸ ਸ ਸ\nਜਿ ਨ ਕ ਉ ਨਦ ਰਿ ਕ ਰੇ\nਮਹਲਾ ੨ ॥\nਆਪੇ ਸਾਜੇ ਕਰੇ ਆਪਿ ਜਾਈ ਭਿ ਰਖੈ ਆਪਿ ॥\nਤਿਸੁ ਵਿਚਿ ਜੰਤ ਉਪਾਇ ਕੈ ਦੇਖੈ ਥਾਪਿ ਉਥਾਪਿ ॥\nਕਿਸ ਨੋ ਕਹੀਐ ਨਾਨਕਾ ਸਭੁ ਕਿਛੁ ਆਪੇ ਆਪਿ ॥੨॥\n(ਅੰਗ ੪੭੫)\n\nਪਦ ਅਰਥ :\n\nਜਾਈ = ਪੈਦਾ ਕੀਤੀ ਹੋਈ ਨੂੰ, ਸ੍ਰਿਸ਼ਟੀ ਨੂੰ। ਥਾਪਿ = ਥਾਪ ਕੇ, ਟਿਕਾ ਕੇ। ਉਥਾਪਿ = ਨਾਸ ਕਰ ਕੇ । ਸਭੁ ਕਿਛੁ -\n\nਭਾਵ, ਸਭ ਕੁਝ ਕਰਨ ਦੇ ਸਮਰੱਥ ।\n\n212:: ਆਸਾ ਦੀ ਵਾਰ\n",
  "status": "draft",
  "extraction_method": "ocr-tesseract-pan(default-psm)",
  "ocr_confidence_note": "Prose ~95-97% char accuracy (Phase A estimate). Bordered grid tables: ~85-90% for sparse/12-col tables, ~50-65% for dense/16-col tables -- not trustworthy at high density. Inline Aroh/Avroh lines outside tables: inter-syllable spacing collapses, worse than table OCR. All notation flagged needs_manual_transcription regardless."
}